standardize_molecule.py
im_standardize_molecule-0.1.0.dist-info/LICENSE
im_standardize_molecule-0.1.0.dist-info/METADATA
im_standardize_molecule-0.1.0.dist-info/WHEEL
im_standardize_molecule-0.1.0.dist-info/top_level.txt
im_standardize_molecule-0.1.0.dist-info/RECORD
