Metadata-Version: 2.1
Name: im-standardize-molecule
Version: 0.1.0
Summary: Utilities for Molecular Science
Home-page: https://github.com/InformaticsMatters/standardize-molecule
Author: Duncan Peacock
Author-email: dpeacock@informaticsmatters.com
License: GPLv3 License
Keywords: smiles,rdkit
Platform: any
Classifier: Development Status :: 5 - Production/Stable
Classifier: Environment :: Console
Classifier: Intended Audience :: Healthcare Industry
Classifier: Intended Audience :: Science/Research
Classifier: License :: OSI Approved :: MIT License
Classifier: Programming Language :: Python :: 3.8
Classifier: Programming Language :: Python :: 3.9
Classifier: Topic :: Scientific/Engineering :: Medical Science Apps.
Classifier: Topic :: Scientific/Engineering :: Bio-Informatics
Classifier: Topic :: Scientific/Engineering :: Chemistry
Requires-Python: >=3, <4
